zohavi/__init__.py
zohavi/zbase/__init__.py
zohavi/zbase/routes.py
zohavi/zbase/staple.py
zohavi/zbase/templates/zbase/base.html
zohavi/zcelery/__init__.py
zohavi/zcelery/celeryrun.py
zohavi/zcelery/handler.py
zohavi/zcelery/models.py
zohavi/zcelery/routes.py
zohavi/zcelery/templates/_def/beats_view.html
zohavi/zcelery/templates/_def/workers_view.html
zohavi/zcelery/templates/_def/workers_view_script.html
zohavi/zcommon/__init__.py
zohavi/zcommon/common_utils.py
zohavi/zconfig/config_manager.py
zohavi/zconfig/models.py
zohavi/zconfig/tests/log.txt
zohavi/zconfig/tests/migrations/README
zohavi/zconfig/tests/migrations/alembic.ini
zohavi/zconfig/tests/migrations/env.py
zohavi/zconfig/tests/migrations/script.py.mako
zohavi/zconfig/tests/migrations/versions/276c78c4a2b7_.py
zohavi/zconfig/tests/migrations/versions/3c00080e3336_.py
zohavi/zconfig/tests/migrations/versions/6250a38af3b8_.py
zohavi/zconfig/tests/migrations/versions/90fa12a8be54_.py
zohavi/zconfig/tests/sys_config.json
zohavi/zconfig/tests/test_config.py
zohavi/zconfig/tests/test_db_config_defaults.json
zohavi/zcore/__init__py
zohavi/zcore/appcore.py
zohavi/zcore/tests/sys_config.json
zohavi/zcore/tests/test_zcore.py
zohavi/zdb/models.py
zohavi/zemailer/__init__.py
zohavi/zemailer/emailer.py
zohavi/zemailer/templates/zemail/email_signature.html
zohavi/zemailer/templates/zemail/email_signature.txt
zohavi/zerrors/__init__.py
zohavi/zerrors/routes.py
zohavi/zerrors/static/_def/images/404.jpg
zohavi/zerrors/static/_def/images/404_looked.jpg
zohavi/zerrors/static/_def/images/404_looked.png
zohavi/zerrors/templates/zerrors/404.html
zohavi/zerrors/templates/zerrors/500.html
zohavi/zerrors/templates/zerrors/base_error.html
zohavi/zerrors/templates/zerrors/user_noaccess.html
zohavi/zerrors/tests/test_zerrors.py
zohavi/zmembers/__init__.py
zohavi/zmembers/routes.py
zohavi/zmembers/templates/zmembers/base_members.html
zohavi/zwebui/__init__.py
zohavi/zwebui/data_ui_model.py
zohavi/zwebui/jinja_cust_funcs.py
zohavi-0.1.49.dist-info/WHEEL
zohavi-0.1.49.dist-info/METADATA
zohavi-0.1.49.dist-info/RECORD
